rwswrap/RWS.py
rwswrap/__init__.py
rwswrap-0.1.0.dist-info/LICENSE
rwswrap-0.1.0.dist-info/METADATA
rwswrap-0.1.0.dist-info/WHEEL
rwswrap-0.1.0.dist-info/top_level.txt
rwswrap-0.1.0.dist-info/RECORD
