Metadata-Version: 2.1
Name: rwswrap
Version: 0.1.0
Summary: A small wrapper for ABB's RobotWebServices API, for RobotWare 7
Home-page: https://github.com/andreasstrom/RWS-wrapper
Author: Andreas Ström
Author-email: andreascstrom@gmail.com
License: UNKNOWN
Platform: UNKNOWN
Classifier: Programming Language :: Python :: 3
Classifier: License :: OSI Approved :: MIT License
Classifier: Operating System :: OS Independent
Requires-Python: >=3.7
License-File: LICENSE
